.gitignore
MANIFEST.in
README.txt
setup.py
collective/__init__.py
collective.blog.view.egg-info/PKG-INFO
collective.blog.view.egg-info/SOURCES.txt
collective.blog.view.egg-info/dependency_links.txt
collective.blog.view.egg-info/entry_points.txt
collective.blog.view.egg-info/namespace_packages.txt
collective.blog.view.egg-info/not-zip-safe
collective.blog.view.egg-info/requires.txt
collective.blog.view.egg-info/top_level.txt
collective/blog/__init__.py
collective/blog/view/__init__.py
collective/blog/view/adapters.py
collective/blog/view/blog.pt
collective/blog/view/blog.py
collective/blog/view/configure.zcml
collective/blog/view/default_item.pt
collective/blog/view/default_item.py
collective/blog/view/i18n.sh
collective/blog/view/interfaces.py
collective/blog/view/testlogo.jpg
collective/blog/view/tests.py
collective/blog/view/locales/collective.blog.view-manual.pot
collective/blog/view/locales/collective.blog.view.pot
collective/blog/view/locales/plone.pot
collective/blog/view/locales/de/LC_MESSAGES/collective.blog.view.po
collective/blog/view/locales/de/LC_MESSAGES/plone.po
collective/blog/view/locales/en/LC_MESSAGES/collective.blog.view.po
collective/blog/view/locales/en/LC_MESSAGES/plone.po
collective/blog/view/locales/es/LC_MESSAGES/collective.blog.view.po
collective/blog/view/locales/es/LC_MESSAGES/plone.po
collective/blog/view/locales/eu/LC_MESSAGES/collective.blog.view.po
collective/blog/view/locales/eu/LC_MESSAGES/plone.po
collective/blog/view/locales/it/LC_MESSAGES/collective.blog.view.po
collective/blog/view/locales/it/LC_MESSAGES/plone.po
collective/blog/view/locales/no/LC_MESSAGES/collective.blog.view.po
collective/blog/view/locales/no/LC_MESSAGES/plone.po
collective/blog/view/locales/sv/LC_MESSAGES/collective.blog.view.po
collective/blog/view/locales/sv/LC_MESSAGES/plone.po
collective/blog/view/profiles/default/propertiestool.xml
collective/blog/view/profiles/default/types.xml
collective/blog/view/profiles/default/types/Folder.xml
collective/blog/view/profiles/default/types/Large_Plone_Folder.xml
collective/blog/view/profiles/default/types/Topic.xml
docs/HISTORY.txt
docs/INSTALL.txt
docs/LICENSE.GPL
docs/LICENSE.txt