Metadata-Version: 1.1
Name: collective.blog.view
Version: 1.5.1
Summary: A blog view for folders.
Home-page: http://svn.plone.org/svn/collective/collective.blog.view/
Author: Jarn AS
Author-email: info@jarn.com
License: GPL
Keywords: plone blog view
Platform: UNKNOWN
Classifier: Framework :: Plone
Classifier: Framework :: Plone :: 4.0
Classifier: Framework :: Plone :: 4.1
Classifier: Framework :: Plone :: 4.2
Classifier: Framework :: Plone :: 4.3
Classifier: Programming Language :: Python
Classifier: Programming Language :: Python :: 2.6
Classifier: Programming Language :: Python :: 2.7
